shipsnake/LICENSE.txt
shipsnake/__init__.py
shipsnake/__main__.py
shipsnake/actions.py
shipsnake/build.py
shipsnake/gitignore.template
shipsnake/readme.py
shipsnake/readme.template
shipsnake/release.py
shipsnake/settings.py.template
shipsnake/setup.py.template
shipsnake/shipsnake.yml.template
shipsnake/wizard.py
shipsnake-0.0.57.data/scripts/shipsnake
shipsnake-0.0.57.dist-info/LICENSE
shipsnake-0.0.57.dist-info/METADATA
shipsnake-0.0.57.dist-info/WHEEL
shipsnake-0.0.57.dist-info/top_level.txt
shipsnake-0.0.57.dist-info/RECORD
