Metadata-Version: 2.1
Name: shipsnake
Version: 0.0.57
Summary: A quick and easy way to distribute your python projects!
Home-page: https://github.com/cole-wilson/shipsnake
Author: Cole Wilson
Author-email: cole@colewilson.xyz
License: MIT
Keywords: ship distribute package snake python freeze shipsnake setuptools
Platform: UNKNOWN
Classifier: Programming Language :: Python :: 3
Requires-Python: >=3.6
Requires-Dist: toml
Requires-Dist: githubrelease
